miniminiai/__init__.py
miniminiai/miniminiai.py
miniminiai/version.py
miniminiai-0.0.5.dist-info/METADATA
miniminiai-0.0.5.dist-info/WHEEL
miniminiai-0.0.5.dist-info/top_level.txt
miniminiai-0.0.5.dist-info/RECORD
