Metadata-Version: 2.1
Name: miniminiai
Version: 0.0.5
Summary: A mini version of fastai's miniai
Home-page: https://github.com/johnowhitaker/miniminiai
Author: Johno Whitaker
License: MIT
Keywords: artificial intelligence,pytorch,machine learning,machine learning framework,fastai
Classifier: Development Status :: 4 - Beta
Classifier: Intended Audience :: Developers
Classifier: Topic :: Scientific/Engineering :: Artificial Intelligence
Classifier: License :: OSI Approved :: MIT License
Classifier: Programming Language :: Python :: 3.10
Requires-Dist: torch
Requires-Dist: fastcore
Requires-Dist: fastprogress
Requires-Dist: numpy
Requires-Dist: matplotlib
Requires-Dist: torcheval
Requires-Dist: torchvision
Requires-Dist: einops
Requires-Dist: accelerate
